zplane/__init__.py
zplane/discrete.py
zplane-0.1.7.dist-info/LICENSE
zplane-0.1.7.dist-info/METADATA
zplane-0.1.7.dist-info/WHEEL
zplane-0.1.7.dist-info/top_level.txt
zplane-0.1.7.dist-info/RECORD
