Metadata-Version: 2.1
Name: zplane
Version: 0.1.7
Summary: Wrapper for scipy's signal module, simplifying a handful of commonly used, discrete system plots.
Home-page: https://github.com/Attrup/zplane
Author: Jonas Attrup
Author-email: attrup.jonas@gmail.com
Keywords: matplotlib,scipy,digital signal processing,discrete,bode,polezero,impulse,frequency
Classifier: Development Status :: 3 - Alpha
Classifier: Intended Audience :: Education
Classifier: License :: OSI Approved :: MIT License
Classifier: Programming Language :: Python :: 3
Classifier: Topic :: Scientific/Engineering
Requires-Python: >=3.10, <4
License-File: LICENSE
Requires-Dist: matplotlib
Requires-Dist: scipy
Requires-Dist: numpy
